ttp_sros_parser/.gitignore
ttp_sros_parser/__init__.py
ttp_sros_parser/helpers.py
ttp_sros_parser/srosparser.py
ttp_sros_parser/templates/__init__.py
ttp_sros_parser/templates/admin_display_file/sros_7750_lag.ttp
ttp_sros_parser/templates/admin_display_file/sros_7750_mpls_lsp.ttp
ttp_sros_parser/templates/admin_display_file/sros_connector_configuration.ttp
ttp_sros_parser/templates/admin_display_file/sros_log_configuration.ttp
ttp_sros_parser/templates/admin_display_file/sros_port_config.ttp
ttp_sros_parser/templates/admin_display_file/sros_router_interface.ttp
ttp_sros_parser/templates/admin_display_file/sros_router_static_routes.ttp
ttp_sros_parser/templates/admin_display_file/sros_system_cards.ttp
ttp_sros_parser/templates/admin_display_file/sros_system_configuration.ttp
ttp_sros_parser/templates/admin_display_file/sros_system_ethcfm.ttp
ttp_sros_parser/templates/admin_display_file/sros_system_maf.ttp
ttp_sros_parser/templates/admin_display_file/sros_system_profiles.ttp
ttp_sros_parser/templates/admin_display_file/sros_system_service_sdp.ttp
ttp_sros_parser/templates/admin_display_file/static-route-bkup
ttp_sros_parser/templates/custom/sros_custom_hostname_asn.ttp
ttp_sros_parser/templates/full_config/sros_full_config.ttp
ttp_sros_parser/templates/helpers/sros_system_asn.ttp
ttp_sros_parser/templates/helpers/sros_system_hostname.ttp
ttp_sros_parser/templates/helpers/sros_system_interface.ttp
ttp_sros_parser/templates/show_commands/show_router_router_table_general.ttp
ttp_sros_parser/templates/show_commands/sros_file_dir.ttp
ttp_sros_parser/templates/show_commands/sros_show_bof_cli.ttp
ttp_sros_parser/templates/show_commands/sros_show_router_interface.ttp
ttp_sros_parser/templates/show_commands/sros_show_router_route_table.ttp
ttp_sros_parser/templates/show_commands/sros_show_router_static_route_ipv4.ttp
ttp_sros_parser/templates/show_commands/sros_show_router_static_route_ipv6.ttp
ttp_sros_parser/templates/show_commands/sros_show_service_service_using.ttp
ttp_sros_parser-0.1.6.dist-info/LICENSE
ttp_sros_parser-0.1.6.dist-info/WHEEL
ttp_sros_parser-0.1.6.dist-info/METADATA
ttp_sros_parser-0.1.6.dist-info/RECORD
