Metadata-Version: 2.1
Name: ttp-sros-parser
Version: 0.1.6
Summary: Utility to parse a full SROS Configuration.
Home-page: https://github.com/h4ndzdatm0ld/ttp_sros_parser
Keywords: sros,ttp,ttp-templates,network automation,nokia,7750
Author: Hugo
Author-email: hugotinoco@icloud.com
Requires-Python: >=3.8,<4.0
Classifier: Programming Language :: Python :: 3
Classifier: Programming Language :: Python :: 3.10
Classifier: Programming Language :: Python :: 3.8
Classifier: Programming Language :: Python :: 3.9
Requires-Dist: ttp (==0.7.2)
Project-URL: Repository, https://github.com/h4ndzdatm0ld/ttp_sros_parser
